rcssl
