Metadata-Version: 1.0
Name: rcssl
Version: 1.3
Summary: Install Let's Encrypt SSL on RunCloud servers the easy way.
Home-page: https://github.com/rehmatworks/runcloud-letsencrypt
Author: Rehmat
Author-email: contact@rehmat.works
License: MIT
Platform: UNKNOWN
